{
  "round": "221",
  "domain_proposed": "paper-marbling-ebru-suminagashi",
  "form_proposed": "information-cascade",
  "memory_check": {
    "domain_prior_fail_count": 0,
    "mechanism_keyword_overlap": [],
    "form_use_count_so_far": 9
  },
  "decision": "ACCEPT",
  "blocked_domains_consulted": ["all epoch 1-8 + saturation_evidence.md priors"],
  "note": "Paper marbling (Turkish ebru / Japanese suminagashi pattern formation on viscous size surface) not tested. R046 lock-in + interference (different signal-recovery), R028 Zipf RAG (different ranking) were the closest prior. Carrageenan-size pigment-floating mechanism is distinct."
}
