{
  "round": "227",
  "results": [
    {"url": "https://falconryadvice.com/equipment/falconry-hood-training-guide/", "keyword_overlap_count": 2, "keyword_overlap_words": ["falconry hood", "manning protocol"], "semantic_cosine": 0.18, "judge_score": 0.05, "forced_by_rule": true, "hit": true},
    {"url": "https://nysfa.org/becoming-a-falconer/husbandry-equipment/hooding/", "keyword_overlap_count": 1, "keyword_overlap_words": ["falconry hood"], "semantic_cosine": 0.14, "judge_score": 0.04, "hit": false},
    {"url": "https://en.wikipedia.org/wiki/Falconry_training_and_technique", "keyword_overlap_count": 2, "keyword_overlap_words": ["falconry hood", "manning protocol"], "semantic_cosine": 0.18, "judge_score": 0.04, "forced_by_rule": true, "hit": true},
    {"url": "https://avian-behavior.org/hooding-and-birds-of-prey/", "keyword_overlap_count": 1, "keyword_overlap_words": ["falconry hood"], "semantic_cosine": 0.16, "judge_score": 0.04, "hit": false},
    {"url": "https://arxiv.org/abs/2603.01494", "keyword_overlap_count": 1, "keyword_overlap_words": ["per-request safety firewall"], "semantic_cosine": 0.55, "judge_score": 0.50, "hit": false},
    {"url": "https://arxiv.org/abs/2511.04847", "keyword_overlap_count": 0, "semantic_cosine": 0.52, "judge_score": 0.45, "hit": false},
    {"url": "https://arxiv.org/html/2410.02725v1", "keyword_overlap_count": 1, "keyword_overlap_words": ["inference-time hood schedule"], "semantic_cosine": 0.72, "judge_score": 0.78, "forced_by_semantic": true, "forced_by_functional": true, "hit": true},
    {"url": "https://arxiv.org/abs/2502.12521", "keyword_overlap_count": 0, "semantic_cosine": 0.60, "judge_score": 0.50, "hit": false}
  ],
  "total_hits": 3,
  "forced_by_rule_keyword_count": 2,
  "forced_by_semantic_count": 1,
  "forced_by_functional_count": 1,
  "verdict": "FAIL — Pattern A (source-domain kw on falconry pages) + Pattern D (Adaptive Inference-Time Compute 2410.02725 covers per-input adaptive temperature anneal — the core functional leg of the hood-anneal proposal)."
}
