{"round": "394", "verdict": "FAIL", "reason": "total_hits = 8. MatryoshkaLoRA (2605.07850, judge 0.88) creates hierarchical low-rank sub-rank structure via diagonal-between-LoRA adapters. HiLo (2502.03884) flexibly adjusts NUMBER+RANK of adapter experts across layers. ARD-LoRA + NormAL LoRA + MeteoRA + heterogeneous-LoRA-serving + X-LoRA + Dynamic LoRA Adapters all densely cover heterogeneous-rank multi-level adapter space.", "total_hits": 8, "channels": {"keyword": 0, "semantic": 8, "functional": 8}}
