{"round": "351", "verdict": "FAIL", "reason": "total_hits = 7. Parallel-decode literature is densely populated: PASTA semantically-independent parallel chunks (2502.11517) + PPD hardware-aware parallel prompt decoding (EMNLP 2025) + Learn2PD learnable parallel decoder (2509.25188) + Parallel Token Prediction (2512.21323 ICLR 2026) + multi-token-prediction draft (2507.11851) + Intervening Anchor Token decoding (ICLR 2025) + Semantic Anchors in ICL (2511.21038). Anchor-grounded N-branch parallel decode is occupied across multiple sub-clusters of this literature.", "total_hits": 7, "channels": {"keyword": 0, "semantic": 7, "functional": 7}}
