{"snippet_id": "S018", "transcript_id": "T001", "start_line": 168, "end_line": 181, "verbatim_text": "And then we want to construct a patch transformer where we patch in components from the second language model to the first one. In the full paper we had some experiments where we localized where different propositions lived inside the network. So suppose Jack possesses the book lives in these two activations. Janet possesses the book lives in these two. Then we're going to patch in these specific propositions. And supposedly what the LM should believe now is that Jack and Janet both possess the book. And then we're going to generate things from this patch transformer. So suppose it generates things like Jack lost a book and Janet lost a book. So the question we're going to ask here is are these completions more likely to be coherent with this patched representation or this patched state than generations from either the original context or this new context? So we're going to plot the coherence of generations to this patched state from each context. So here the first completion is not consistent with this patched state. The second one is. So there's a 50 percent consistency rate. In this context the first one is also not consistent.", "boundary_justification": "reason=max_sentences_reached; sentence_count=14; topic_shift_markers=none", "sentence_count": 14, "char_count": 1148}