{"snippet_id": "S002", "transcript_id": "T010", "start_line": 15, "end_line": 28, "verbatim_text": "So we're gonna make our neural net out of artificial neurons. And an artificial neuron is gonna have some input lines, typically coming from other neurons, it's gonna have weights on those input lines. It's gonna multiply the inputs by the weights, add all up, and then give an output, which is shown by that graph there. So if it gets above its threshold, it gives an output that linearly increases as it gets more input. And the way it's gonna learn is just by changing the weights on those connections. So all we need to do to make artificial neural networks work is figure out how to change the weights. We hook them up into networks. This is a typical network, it's a feedforward network, where at the bottom, you might have sensory neurons that are recording light intensities or something like that. And as you go up through the layers, you have many layers of feature detectors that is the neurons turn into things that recognise particular features in an image. And at the output, you might have neurons to represent particular classes of thing. Now, if you want a network like that to learn to be better at doing something, so. You want to give it an image and have it say, for example, whether there's a cat or a dog, there's an obvious way to train it, which goes to everybody who knows about evolution and. What you can do is, you can take one of the weights, and you can first see how. Well the network does on a whole bunch of examples, and then change the weight just slightly, and see how.", "boundary_justification": "reason=max_sentences_reached; sentence_count=14; topic_shift_markers=none", "sentence_count": 14, "char_count": 1506}