{"round": "465", "rule": "hit iff kw>=2 OR sem>=0.7 OR func>=0.7", "content_words": ["oromo gada generation class system", "8-year term 11-grade rotation cycle", "salgan ya'ii borana 9-leader consensus", "balanced opposition power-share principles", "5-class rotating specialization power cycle", "11-grade within-class skill progression", "consensus-9 Salgan delegate selection", "three-principle term opposition power-share"], "results": [{"rank": 1, "url": "https://openreview.net/pdf/2f422b2f6134e98bed024e119abc1c7642166c79.pdf", "kw_count": 0, "sem_cosine": 0.90, "func_score": 0.90, "hit": true, "forced_by_rule": false, "forced_by_semantic": true, "forced_by_functional": true}, {"rank": 2, "url": "https://arxiv.org/pdf/2504.00587", "kw_count": 0, "sem_cosine": 0.86, "func_score": 0.86, "hit": true, "forced_by_rule": false, "forced_by_semantic": true, "forced_by_functional": true}, {"rank": 3, "url": "https://dl.acm.org/doi/full/10.1145/3772363.3778738", "kw_count": 0, "sem_cosine": 0.84, "func_score": 0.84, "hit": true, "forced_by_rule": false, "forced_by_semantic": true, "forced_by_functional": true}, {"rank": 4, "url": "https://arxiv.org/html/2508.04652v1", "kw_count": 0, "sem_cosine": 0.88, "func_score": 0.86, "hit": true, "forced_by_rule": false, "forced_by_semantic": true, "forced_by_functional": true}, {"rank": 5, "url": "https://arxiv.org/html/2605.02801v1", "kw_count": 0, "sem_cosine": 0.82, "func_score": 0.82, "hit": true, "forced_by_rule": false, "forced_by_semantic": true, "forced_by_functional": true}, {"rank": 6, "url": "https://www.codebridge.tech/articles/mastering-multi-agent-orchestration-coordination-is-the-new-scale-frontier", "kw_count": 0, "sem_cosine": 0.80, "func_score": 0.80, "hit": true, "forced_by_rule": false, "forced_by_semantic": true, "forced_by_functional": true}, {"rank": 7, "url": "https://arxiv.org/html/2404.04834v4", "kw_count": 0, "sem_cosine": 0.78, "func_score": 0.78, "hit": true, "forced_by_rule": false, "forced_by_semantic": true, "forced_by_functional": true}, {"rank": 8, "url": "https://www.preprints.org/manuscript/202511.1370/v1/download", "kw_count": 0, "sem_cosine": 0.74, "func_score": 0.74, "hit": true, "forced_by_rule": false, "forced_by_semantic": true, "forced_by_functional": true}], "total_hits": 8, "kw_forced_hits": 0, "semantic_forced_hits": 8, "functional_forced_hits": 8}
