{"round":"680","epoch":28,"active_scenarios":["S_capability","S_safety"],"scenarios":[
{"scenario_id":"S_capability","scenario_rationale":"hierarchical reasoning parallel rewriting","perspectives":[{"perspective_id":"P_prior_art","criteria":[{"id":"C1","weight":0.5,"check":"kw>=2","fired":true,"evidence_field":"4"},{"id":"C2","weight":0.3,"check":"sem>=0.7","fired":false,"evidence_field":"0.62"},{"id":"C3","weight":0.2,"check":"func>=0.7","fired":false,"evidence_field":"0.55"}],"perspective_score":0.5},{"perspective_id":"P_obfuscation","criteria":[{"id":"C1","weight":0.5,"check":"metaphor","fired":false,"evidence_field":"shared_math"},{"id":"C2","weight":0.5,"check":"stripping","fired":true,"evidence_field":"yes"}],"perspective_score":0.5},{"perspective_id":"P_composition","criteria":[{"id":"C1","weight":0.6,"check":"K-1","fired":false,"evidence_field":"max 2/4"},{"id":"C2","weight":0.4,"check":"-","fired":false,"evidence_field":"-"}],"perspective_score":0.0},{"perspective_id":"P_evidence","criteria":[{"id":"C1","weight":0.5,"check":">=3","fired":true,"evidence_field":"3"},{"id":"C2","weight":0.5,"check":">=1","fired":true,"evidence_field":"3"}],"perspective_score":1.0}],"scenario_score":0.5},
{"scenario_id":"S_safety","scenario_rationale":"bounded recursion","perspectives":[{"perspective_id":"P_prior_art","criteria":[{"id":"C1","weight":0.5,"check":"kw>=2","fired":true,"evidence_field":"4"},{"id":"C2","weight":0.3,"check":"sem>=0.7","fired":false,"evidence_field":"0.62"},{"id":"C3","weight":0.2,"check":"func>=0.7","fired":false,"evidence_field":"0.55"}],"perspective_score":0.5},{"perspective_id":"P_obfuscation","criteria":[{"id":"C1","weight":0.5,"check":"metaphor","fired":false,"evidence_field":"-"},{"id":"C2","weight":0.5,"check":"stripping","fired":true,"evidence_field":"yes"}],"perspective_score":0.5},{"perspective_id":"P_composition","criteria":[{"id":"C1","weight":0.6,"check":"K-1","fired":false,"evidence_field":"-"},{"id":"C2","weight":0.4,"check":"-","fired":false,"evidence_field":"-"}],"perspective_score":0.0},{"perspective_id":"P_evidence","criteria":[{"id":"C1","weight":0.5,"check":">=3","fired":true,"evidence_field":"-"},{"id":"C2","weight":0.5,"check":">=1","fired":true,"evidence_field":"-"}],"perspective_score":1.0}],"scenario_score":0.5}],
"q_rubric_score":0.5,"q_rubric_verdict":"ANTICIPATED","q_rubric_aligns_with_step_10":true,"q_rubric_aligns_with_step_12_tree_stream":true,"q_rubric_aligns_with_gap_position":true}
