{"round":"636","epoch":26,"timestamp":"2026-05-19T19:43:30Z","results":[
  {"title":"Riemannian LoRA on Stiefel (EMNLP 2025, arXiv 2508.17901)","url":"https://arxiv.org/abs/2508.17901"},
  {"title":"StelLA NeurIPS 2025 Spotlight","url":"https://github.com/SonyResearch/stella"},
  {"title":"Retraction-free Stiefel LoRA (openreview ICLR 2025)","url":"https://openreview.net/forum?id=c2OtbtZXFC"},
  {"title":"Calibrated Bayesian Stiefel Priors (arXiv 2602.17809)","url":"https://arxiv.org/abs/2602.17809"}
]}
