{"round": "895", "epoch": 36, "v17_index": true, "kcd_database_size": 4, "attempts": [{"attempt": 1, "candidate_strategy": "B", "candidate_mech": "Lie-group-equivariance token routing combination (S16+S19)", "candidate_embedding_keys": ["Lie", "equivariance", "SU2", "SU(2)", "permutation", "group", "equivariant", "invariance", "Heisenberg", "Quaternion"], "max_similarity": 0.714, "matched_entry_id": "KCD_7CLUSTER", "kcd_threshold": 0.5, "verdict": "REJECTED_KNOWN_COLLISION", "per_entry_sims": [{"entry_id": "KCD_R279", "similarity": 0.0}, {"entry_id": "KCD_R827", "similarity": 0.0}, {"entry_id": "KCD_R855", "similarity": 0.0}, {"entry_id": "KCD_7CLUSTER", "similarity": 0.714}]}, {"attempt": 2, "candidate_strategy": "D", "candidate_mech": "Polynomial-time-bounded token routing (negation: NOT-Lie-NOT-equivariance-NOT-divergence-NOT-spectral)", "candidate_embedding_keys": ["complexi", "S16", "Polynomial-tim", "NEW module", "NEW pathway", "architectural-topology", "collision-negation", "NOT-Lie", "NOT-equivariance", "NOT-divergence", "NOT-spectral"], "max_similarity": 0.05, "matched_entry_id": "KCD_7CLUSTER", "kcd_threshold": 0.5, "verdict": "PASS", "per_entry_sims": [{"entry_id": "KCD_R279", "similarity": 0.0}, {"entry_id": "KCD_R827", "similarity": 0.0}, {"entry_id": "KCD_R855", "similarity": 0.0}, {"entry_id": "KCD_7CLUSTER", "similarity": 0.05}]}], "final_verdict": "PASS", "timestamp": "2026-05-21T23:57:00Z"}