[
  {
    "cand_id": "CAND_016_001",
    "niche_name": "Similarity-Preserving Routing for Test-Time-Training Mixture-of-Experts",
    "composite": 0.45,
    "composite_params": {
      "novelty": 0.0,
      "mechanism_present": 1.0,
      "quote_grounded": 1.0,
      "cross_atom": 1.0
    },
    "gate_1_composite": {
      "pass": false,
      "composite": 0.45,
      "threshold": 0.9
    },
    "gate_2_quarantine": {
      "pass": true,
      "quarantine_hits": []
    },
    "gate_3_verify": {
      "pass": true,
      "n_reformulations": 5,
      "required": 5,
      "verifier_collision": false,
      "crosscheck_overturned": false
    },
    "gate_4_belinda": {
      "pass": true,
      "mechanism_verbs": [
        "induces",
        "regulates"
      ],
      "quote_len": 142,
      "quote_grounded": true,
      "quote_source_id": "ATOM_R16E3_01"
    },
    "survived": false,
    "gates_failed": [
      "gate_1_composite"
    ]
  },
  {
    "cand_id": "CAND_016_002",
    "niche_name": "Rupture Dynamics of Test-Time-Training Hidden States",
    "composite": 0.45,
    "composite_params": {
      "novelty": 0.0,
      "mechanism_present": 1.0,
      "quote_grounded": 1.0,
      "cross_atom": 1.0
    },
    "gate_1_composite": {
      "pass": false,
      "composite": 0.45,
      "threshold": 0.9
    },
    "gate_2_quarantine": {
      "pass": true,
      "quarantine_hits": []
    },
    "gate_3_verify": {
      "pass": true,
      "n_reformulations": 5,
      "required": 5,
      "verifier_collision": false,
      "crosscheck_overturned": false
    },
    "gate_4_belinda": {
      "pass": true,
      "mechanism_verbs": [
        "induces"
      ],
      "quote_len": 66,
      "quote_grounded": true,
      "quote_source_id": "ATOM_R16E3_03"
    },
    "survived": false,
    "gates_failed": [
      "gate_1_composite"
    ]
  },
  {
    "cand_id": "CAND_016_003",
    "niche_name": "Damage-Regularized Orthogonal Routing for Stable MoE Load Balancing",
    "composite": 0.45,
    "composite_params": {
      "novelty": 0.0,
      "mechanism_present": 1.0,
      "quote_grounded": 1.0,
      "cross_atom": 1.0
    },
    "gate_1_composite": {
      "pass": false,
      "composite": 0.45,
      "threshold": 0.9
    },
    "gate_2_quarantine": {
      "pass": true,
      "quarantine_hits": []
    },
    "gate_3_verify": {
      "pass": true,
      "n_reformulations": 5,
      "required": 5,
      "verifier_collision": false,
      "crosscheck_overturned": false
    },
    "gate_4_belinda": {
      "pass": true,
      "mechanism_verbs": [
        "induces",
        "produces",
        "reduces",
        "regulates"
      ],
      "quote_len": 54,
      "quote_grounded": true,
      "quote_source_id": "ATOM_R16E3_01"
    },
    "survived": false,
    "gates_failed": [
      "gate_1_composite"
    ]
  }
]