{"round":"727","epoch":30,"step":"07_hit_miss","keyword_threshold":2,"per_result_keywords":[{"rank":1,"paper":"Mostly Know","keyword_overlap_count":3,"matched_words":["self","prediction","calibration"],"hit":true},{"rank":2,"paper":"P(IK)","keyword_overlap_count":3,"matched_words":["self","knowledge","fail"],"hit":true},{"rank":3,"paper":"Self-Evaluation","keyword_overlap_count":2,"matched_words":["self","evaluation"],"hit":true}],"keyword_hit_count_total":3,"hit_papers_count":3,"verdict_input_to_step_10":3}
