{"round": "524", "verdict": "FAIL", "reason": "total_hits = 8. HERMES Multi-Stage 2504.09775 (judge 0.86) EXACT TWIN + Dual-Gated SFT 2602.01034 EXACT TWIN + IDK-YES-NO Gating Cascade EXACT TWIN + SinkTrack BOS Anchor EXACT TWIN + Self-Anchor Step-by-Step Alignment EXACT TWIN + Multi-Step Reasoning Survey + Preplan-Anchor Rhythm + Multimodal Rotation. Multi-stage pipeline + completion-gate + attention-anchor + step-alignment paradigm fully covered.", "total_hits": 8, "channels": {"keyword": 0, "semantic": 8, "functional": 8}}
