{"round":"590","K_sub_mechanisms":5,"sub_mechanisms":["M_1 P_4day","M_2 K_role","M_3 R_quad","M_4 A_orch","M_5 G_purify"],"completeness_threshold":0.7,"results":[{"rank":1,"completeness_score":0.26,"covered":["M_1 partial"],"missing":["M_2","M_3","M_4","M_5"],"per_paper_completeness_hit":false},{"rank":2,"completeness_score":0.24,"covered":["M_2 partial"],"missing":["M_1","M_3","M_4","M_5"],"per_paper_completeness_hit":false},{"rank":3,"completeness_score":0.20,"covered":["M_3 partial"],"missing":["M_1","M_2","M_4","M_5"],"per_paper_completeness_hit":false},{"rank":4,"completeness_score":0.18,"covered":["M_1 partial"],"missing":["M_2","M_3","M_4","M_5"],"per_paper_completeness_hit":false},{"rank":5,"completeness_score":0.18,"covered":["M_2 partial"],"missing":["M_1","M_3","M_4","M_5"],"per_paper_completeness_hit":false},{"rank":6,"completeness_score":0.22,"covered":["M_4 partial"],"missing":["M_1","M_2","M_3","M_5"],"per_paper_completeness_hit":false},{"rank":7,"completeness_score":0.14,"covered":[],"missing":["M_1","M_2","M_3","M_4","M_5"],"per_paper_completeness_hit":false},{"rank":8,"completeness_score":0.16,"covered":["M_2 partial"],"missing":["M_1","M_3","M_4","M_5"],"per_paper_completeness_hit":false}],"summary":{"per_paper_completeness_hits_count":0,"max_completeness_score":0.26}}
