{
  "snippet_id": "S038",
  "transcript_id": "T009",
  "start_line": 506,
  "end_line": 519,
  "verbatim_text": "And some of the reasons for this, again, you're always on call. So maybe you don't intend to work all parts of the day. But you might not get to control which ones. You're a role model, this is super important. So if you're an employee of a company , you might have some good weeks, you might have some bad weeks, some weeks when you're, you're low energy, maybe you wanna take a couple extra days off , that's really bad if you're, you're an entrepreneur like your team will really signal off what your bringing to the table. And so if you take your foot off the gas, so will they. And you're always working anyway. So, if you're really passionate about an idea, it's just gonna like pull you to, to keep working on it. If you're working with great investors, you're working with great partners, they're gonna wanna be working really hard, they're gonna want you to be working really hard , and again, you're gonna wanna work really hard. So some some companies like to tell the story about you can have your cake and eat it too, you can have, , four day week, work weeks maybe if you're, if you're, Tim Ferris maybe you can have a 12-hour work week. It's a really attractive idea and it does work in a particular instance. Which is if you wanna like actually have a small business or go after a niche market. Then you're a small business entrepreneur. That makes total sense.",
  "boundary_justification": "reason=max_sentences_reached; sentence_count=14; topic_shift_markers=none",
  "sentence_count": 14,
  "char_count": 1377
}