{
  "round": "628",
  "epoch": 26,
  "results": [
    {"rank": 1, "url": "https://arxiv.org/abs/2602.01685", "keyword_overlap_count": 3, "semantic_hit": true, "functional_hit": true, "hit": true, "forced_by_rule": true},
    {"rank": 2, "url": "https://arxiv.org/abs/2502.06061", "keyword_overlap_count": 2, "hit": true, "forced_by_rule": true},
    {"rank": 3, "url": "https://www.shadecoder.com/topics/kantorovich-rubinstein-duality-a-comprehensive-guide-for-2025", "keyword_overlap_count": 1, "hit": false},
    {"rank": 4, "url": "https://www.researchgate.net/publication/393450546", "keyword_overlap_count": 1, "hit": false},
    {"rank": 5, "url": "https://arxiv.org/abs/2205.13098", "keyword_overlap_count": 2, "hit": true, "forced_by_rule": true},
    {"rank": 6, "url": "https://arxiv.org/abs/2402.16821", "keyword_overlap_count": 2, "hit": true, "forced_by_rule": true},
    {"rank": 7, "url": "https://arxiv.org/abs/2307.11714", "keyword_overlap_count": 1, "hit": false},
    {"rank": 8, "url": "https://arxiv.org/abs/2601.12415", "keyword_overlap_count": 3, "semantic_hit": true, "functional_hit": true, "hit": true, "forced_by_rule": true},
    {"rank": 9, "url": "https://openreview.net/pdf/34614c3d3ac95fcfe06bce943b377a0fd7f14cce.pdf", "keyword_overlap_count": 2, "semantic_hit": true, "functional_hit": true, "hit": true, "forced_by_rule": true},
    {"rank": 10, "url": "https://arxiv.org/abs/2602.18037", "keyword_overlap_count": 1, "hit": false}
  ],
  "total_hits": 6,
  "keyword_hits": 6,
  "semantic_hits": 3,
  "functional_hits": 3
}
