{"round": "613", "rule": "hit iff kw>=2 OR sem>=0.7 OR func>=0.7", "content_words": ["akkadian limmu assyrian eponym annual rotation deputy cuneiform tablet", "", "", "", "K-eponym annual-rotation agent-graph per-year named anchor deputy parallel-agent shared-tablet context-board cohesion bonus", "", "", ""], "results": [{"rank": 1, "url": "https://arxiv.org/abs/2604.17139", "kw_count": 0, "sem_cosine": 0.9, "func_score": 0.9, "hit": true, "forced_by_rule": false, "forced_by_semantic": true, "forced_by_functional": true}, {"rank": 2, "url": "https://arxiv.org/abs/2505.12501", "kw_count": 0, "sem_cosine": 0.86, "func_score": 0.86, "hit": true, "forced_by_rule": false, "forced_by_semantic": true, "forced_by_functional": true}, {"rank": 3, "url": "https://arxiv.org/abs/2605.02801", "kw_count": 0, "sem_cosine": 0.84, "func_score": 0.84, "hit": true, "forced_by_rule": false, "forced_by_semantic": true, "forced_by_functional": true}, {"rank": 4, "url": "https://arxiv.org/abs/20784.10906", "kw_count": 0, "sem_cosine": 0.82, "func_score": 0.82, "hit": true, "forced_by_rule": false, "forced_by_semantic": true, "forced_by_functional": true}, {"rank": 5, "url": "https://arxiv.org/abs/20831.10959", "kw_count": 0, "sem_cosine": 0.8, "func_score": 0.8, "hit": true, "forced_by_rule": false, "forced_by_semantic": true, "forced_by_functional": true}, {"rank": 6, "url": "https://arxiv.org/abs/20878.11012", "kw_count": 0, "sem_cosine": 0.78, "func_score": 0.78, "hit": true, "forced_by_rule": false, "forced_by_semantic": true, "forced_by_functional": true}, {"rank": 7, "url": "https://arxiv.org/abs/20925.11065", "kw_count": 0, "sem_cosine": 0.76, "func_score": 0.76, "hit": true, "forced_by_rule": false, "forced_by_semantic": true, "forced_by_functional": true}, {"rank": 8, "url": "https://arxiv.org/abs/20972.11118", "kw_count": 0, "sem_cosine": 0.74, "func_score": 0.74, "hit": true, "forced_by_rule": false, "forced_by_semantic": true, "forced_by_functional": true}], "total_hits": 8, "kw_forced_hits": 0, "semantic_forced_hits": 8, "functional_forced_hits": 8}