{
  "proofs": {
    "agents_all_committed": true,
    "report_verbatim": true,
    "four_gate_deterministic": true,
    "no_hallucination": true,
    "every_gate_has_reasoning_trace": true,
    "all_traces_complete": true,
    "per_atom_hits_reported": true,
    "search_quality_computed": true,
    "params_persisted": true,
    "queries_emitted_for_labeling": true,
    "transparency_report_written": true
  },
  "all_pass": true,
  "verdict": "NICHE_NOT_FOUND",
  "scored_epoch": 1,
  "next_epoch": 2,
  "avg_search_quality": 0.7983,
  "avg_search_quality_delta": null,
  "avg_paper_hits": 21.0,
  "avg_paper_hits_delta": null,
  "n_survivors": 0,
  "n_logic_breaks": 0,
  "generated_at": "2026-06-01T22:44:29.470707+00:00"
}