{"round":"632","epoch":26,"threshold":0.7,"results":[
  {"rank":1,"url":"https://arxiv.org/abs/2409.12618","cosine_estimate":0.65,"semantic_hit":false},
  {"rank":2,"url":"https://arxiv.org/abs/2410.13413","cosine_estimate":0.66,"semantic_hit":false},
  {"rank":3,"url":"https://arxiv.org/abs/2510.01123","cosine_estimate":0.60,"semantic_hit":false},
  {"rank":4,"url":"https://arxiv.org/abs/2603.15051","cosine_estimate":0.62,"semantic_hit":false},
  {"rank":5,"url":"https://arxiv.org/abs/2206.15448","cosine_estimate":0.55,"semantic_hit":false},
  {"rank":6,"url":"https://www.ncbi.nlm.nih.gov/pmc/articles/PMC10956829/","cosine_estimate":0.50,"semantic_hit":false},
  {"rank":7,"url":"https://arxiv.org/abs/2510.00579","cosine_estimate":0.58,"semantic_hit":false},
  {"rank":8,"url":"https://arxiv.org/abs/2602.04246","cosine_estimate":0.55,"semantic_hit":false},
  {"rank":9,"url":"https://arxiv.org/abs/2412.06769","cosine_estimate":0.55,"semantic_hit":false}
],"semantic_hits_count":0,"max_cosine":0.66}
