{
  "atom_id": "ATOM_T011_S009_01",
  "atom_type": "NEGATIVE_RESULT",
  "snippet_id": "S009",
  "transcript_id": "T011",
  "line_span": [
    440,
    499
  ],
  "verbatim_quote": "limitations of inference by\nformal propagation through a\nfixed number of operations. A\nlot of things that we're doing\nrequire much more\nsophisticated computation than\nthis.",
  "gloss": "[NEGATIVE_RESULT] limitations of inference by formal propagation through a fixed number of operations. A lot of things that we're doing require much more sophisticated computation than this.",
  "extraction_pattern": "NEGATIVE_RESULT_regex"
}