{
  "atom_id": "ATOM_T011_S017_03",
  "atom_type": "MECHANISM_CLAIM",
  "snippet_id": "S017",
  "transcript_id": "T011",
  "line_span": [
    871,
    917
  ],
  "verbatim_quote": "call jpa, that means joint\nembedding predictive\narchitecture. And basically\ninstead of predicting all the\npixels, we're going to predict\na representation of the\npixels.",
  "gloss": "[MECHANISM_CLAIM] call jpa, that means joint embedding predictive architecture. And basically instead of predicting all the pixels, we're going to predict a representation of the pixels.",
  "extraction_pattern": "MECHANISM_CLAIM_regex"
}