{
  "atom_id": "ATOM_T009_S014_01",
  "atom_type": "NEGATIVE_RESULT",
  "snippet_id": "S014",
  "transcript_id": "T009",
  "line_span": [
    460,
    495
  ],
  "verbatim_quote": "a while you cannot create a\nmarket that doesn't want to\nexist. You can basically\nchange everything in a startup\nbut the market.",
  "gloss": "[NEGATIVE_RESULT] a while you cannot create a market that doesn't want to exist. You can basically change everything in a startup but the market.",
  "extraction_pattern": "NEGATIVE_RESULT_regex"
}