{"round":"779","epoch":32,"step":"02_decomposition","candidate_form":"null-space-traversal","motivation_strength":"shared_math_structure","domain_normalized":"algebraic-topology","mechanism_keywords":["stable homotopy","Goodwillie derivative","Postnikov tower","EilenbergMacLane"],"problem_summary":"Goodwillie-derivative null pathway","sub_mechanisms":["M_1 stable homotopy","M_2 Goodwillie derivative","M_3 Goodwillie-derivative null pathway","M_4 new learnable tower module"],"policy_state_consulted":true,"policy_override":false,"v13_program":"program_v13.md","v13_timestamp":"2026-05-21T14:09:00Z"}
