{
  "atom_id": "ATOM_T007_S029_ANA_01",
  "atom_type": "ANALOGY",
  "paradigm_type": "analogy",
  "snippet_id": "S029",
  "transcript_id": "T007",
  "source_date": null,
  "target_date": null,
  "line_span": [
    398,
    411
  ],
  "verbatim_quote": "But it's some an office macro like functionality and so. Actually you can use app scripts to instead exfiltrate the user data into a Google doc and because it's a Google doc this is within the Google domain and this is considered safe and okay.",
  "gloss": "[ANALOGY] But it's some an office macro like functionality and so. Actually you can use app scripts to instead exfiltrate the user data into a Google doc and because it's a Google doc thi...",
  "extraction_pattern": "analogy_regex"
}