{"round": "302", "rule": "hit iff kw>=2 OR sem>=0.7 OR func>=0.7", "content_words": ["brood X prime cycle", "13/17 year coprime emergence", "predator-period satiation", "rare resonance avoidance", "prime-numbered replay period", "coprime cycle scheduling", "resonance-interference avoidance", "gradient-cycle de-alignment"], "results": [{"rank": 1, "url": "https://en.wikipedia.org/wiki/Periodical_cicadas", "kw_count": 0, "sem_cosine": 0.15, "func_score": 0.05, "hit": false}, {"rank": 2, "url": "https://arxiv.org/html/2509.25087v1", "kw_count": 0, "sem_cosine": 0.45, "func_score": 0.4, "hit": false}, {"rank": 3, "url": "https://arxiv.org/html/2602.01826", "kw_count": 0, "sem_cosine": 0.58, "func_score": 0.6, "hit": false}, {"rank": 4, "url": "https://arxiv.org/html/2605.00435", "kw_count": 0, "sem_cosine": 0.52, "func_score": 0.45, "hit": false}, {"rank": 5, "url": "https://openreview.net/pdf?id=IgZWU75BLL", "kw_count": 0, "sem_cosine": 0.62, "func_score": 0.55, "hit": false}, {"rank": 6, "url": "https://arxiv.org/html/2507.07451v1", "kw_count": 0, "sem_cosine": 0.66, "func_score": 0.6, "hit": false}, {"rank": 7, "url": "https://arxiv.org/html/2603.09892v1", "kw_count": 0, "sem_cosine": 0.68, "func_score": 0.65, "hit": false}, {"rank": 8, "url": "https://arxiv.org/html/2505.12512v1", "kw_count": 0, "sem_cosine": 0.65, "func_score": 0.55, "hit": false}], "total_hits": 0, "kw_forced_hits": 0, "semantic_forced_hits": 0, "functional_forced_hits": 0, "note": "Zero forced hits across all three channels. Closest adjacency MSSR memory-aware adaptive replay (sem 0.68, func 0.65) — same artefact (replay-buffer scheduling) but different selection mechanism (adaptive vs prime-coprime)."}
