{
  "atom_id": "ATOM_T007_S002_ANA_01",
  "atom_type": "ANALOGY",
  "paradigm_type": "analogy",
  "snippet_id": "S002",
  "transcript_id": "T007",
  "source_date": null,
  "target_date": null,
  "line_span": [
    17,
    30
  ],
  "verbatim_quote": "It's two bytes because this is a float 16 number as the data type now in addition to these parameters that's just like a large list of parameters for that neural network you also need something that runs that neural network and. This piece of code is implemented in our run file.",
  "gloss": "[ANALOGY] It's two bytes because this is a float 16 number as the data type now in addition to these parameters that's just like a large list of parameters for that neural network you als...",
  "extraction_pattern": "analogy_regex"
}