{
  "atom_id": "ATOM_T011_S001_PRE_01",
  "atom_type": "PREDICTION",
  "paradigm_type": "prediction",
  "snippet_id": "S001",
  "transcript_id": "T011",
  "source_date": null,
  "target_date": null,
  "line_span": [
    1,
    14
  ],
  "verbatim_quote": "I think of him interchangeably with the idea of convolutional neural nets. I'm a geometer as a mathematician, you know, topologist and geometer.",
  "gloss": "[PREDICTION] I think of him interchangeably with the idea of convolutional neural nets. I'm a geometer as a mathematician, you know, topologist and geometer.",
  "extraction_pattern": "prediction_regex"
}