{
  "atom_id": "ATOM_T001_S001_PRE_02",
  "atom_type": "PREDICTION",
  "paradigm_type": "prediction",
  "snippet_id": "S001",
  "transcript_id": "T001",
  "source_date": null,
  "target_date": null,
  "line_span": [
    1,
    14
  ],
  "verbatim_quote": "And ultimately, I think this leads us to a future of more reliable, adaptive, transparent, and collaborative AI systems. But to truly contextualize what these models are, let's take a look at where this field has been.",
  "gloss": "[PREDICTION] And ultimately, I think this leads us to a future of more reliable, adaptive, transparent, and collaborative AI systems. But to truly contextualize what these models are, let's ...",
  "extraction_pattern": "prediction_regex"
}