{
  "atom_id": "ATOM_T002_S017_02",
  "atom_type": "PRIMITIVE",
  "snippet_id": "S017",
  "transcript_id": "T002",
  "line_span": [
    209,
    222
  ],
  "verbatim_quote": "So, you know, transformers are a core building block of self-attention and which stores the embedding of every word in a growing list.",
  "gloss": "[PRIMITIVE] So, you know, transformers are a core building block of self-attention and which stores the embedding of every word in a growing list.",
  "extraction_pattern": "PRIMITIVE_regex"
}