{"round": "441", "verdict": "FAIL", "reason": "total_hits = 8. Triple EXACT TWIN: LoRA Subtraction 2503.18985 (0.92) sign-negative drift-resistant subtraction, Analysing Safety Steering 2603.24543 (0.90) directional ablation mitigation, COSMIC Refusal Direction Findings ACL 2025 (0.88) negative-steering subtract refusal. LoRA-Null 2503.02659, One-Shot Optimized Steering 2502.18862, Dataset-Corruption Steering, Safe LoRA, OPLoRA cover sign-negative LoRA + direction-ablation + null-space projection across 8 distinct effect clusters.", "total_hits": 8, "channels": {"keyword": 0, "semantic": 8, "functional": 8}}
