{
  "atom_id": "ATOM_T010_S021_ANA_02",
  "atom_type": "ANALOGY",
  "paradigm_type": "analogy",
  "snippet_id": "S021",
  "transcript_id": "T010",
  "source_date": "2025-04-01",
  "target_date": "2025-04-01",
  "line_span": [
    1100,
    1153
  ],
  "verbatim_quote": "like to change my weights to\nabsorb that bit of the data. And some other copy figures\nout how to change its weights\nto absorb a different bit of\ndata.",
  "gloss": "[ANALOGY] like to change my weights to absorb that bit of the data. And some other copy figures out how to change its weights to absorb a different bit of data.",
  "extraction_pattern": "analogy_regex"
}