{
  "snippet_id": "S039",
  "transcript_id": "T003",
  "start_line": 451,
  "end_line": 464,
  "verbatim_text": "And even in terms of, like you mentioned, one of the problems is data scaling for experimental science is, are you able to get internet scale data from physics labs, right? So I guess there's a qualitative difference, as well as a quantitative difference in the actual kind of experiments that we're doing with reasoning models, say, and how it could transfer for science or natural sciences. Right. So to summarize, the question was roughly, how do reasoning scaling laws and things like this, as well as skills, how do these two things translate to actual scientific problems? Well, I think the way I think of these is I think they're two very basic primitives that you're going to need in a lot of applications. So for skills in particular, this is just data, and you're going to need data to train these models. You're going to need data that's relevant for these scientific domains. There's nothing special about skills. This is just a definition that we use to understand how does the data that you train on relate to these downstream tasks that you're evaluating on. And that, as a conceptual primitive, is going to be useful for training these scientific models. As for reasoning, for things like physics, of course, you're going to need to be developing physical descriptions of the universe. These might be very long, and might be very precise, or be intricate, or you might derive them from other things like this. And that's all reasoning. And that's going to come from models that have multiple attempts at generating these things, or maybe think for a really long time before producing some very long answer that's very precise.",
  "boundary_justification": "reason=max_sentences_reached; sentence_count=14; topic_shift_markers=none",
  "sentence_count": 14,
  "char_count": 1642
}