{
  "atom_id": "ATOM_T001_S046_PRE_04",
  "atom_type": "PREDICTION",
  "paradigm_type": "prediction",
  "snippet_id": "S046",
  "transcript_id": "T001",
  "source_date": "2025-06-01",
  "target_date": "2025-06-01",
  "line_span": [
    504,
    517
  ],
  "verbatim_quote": "Second, if we can extract world models from our AI systems, then we can potentially get to a future where we can extract scientific knowledge from systems trained on large scale scientific or simulation corpora. Also, user and self models help us address the specification problem, which we saw earlier.",
  "gloss": "[PREDICTION] Second, if we can extract world models from our AI systems, then we can potentially get to a future where we can extract scientific knowledge from systems trained on large scale...",
  "extraction_pattern": "prediction_regex"
}