{
  "round": "106",
  "results": [
    {
      "url": "https://arxiv.org/abs/2406.4982",
      "title": "Inference Latency Control: Survey",
      "keyword_overlap_count": 1,
      "semantic_cosine": 0.71,
      "judge_score": 0.66,
      "forced_by_rule": false,
      "forced_by_semantic": true,
      "forced_by_functional": false,
      "hit": true
    },
    {
      "url": "https://arxiv.org/abs/2407.6355",
      "title": "Inference Latency Control: Method",
      "keyword_overlap_count": 1,
      "semantic_cosine": 0.59,
      "judge_score": 0.58,
      "forced_by_rule": false,
      "forced_by_semantic": false,
      "forced_by_functional": false,
      "hit": false
    },
    {
      "url": "https://arxiv.org/abs/2416.4982",
      "title": "Inference Latency Control: Survey",
      "keyword_overlap_count": 0,
      "semantic_cosine": 0.53,
      "judge_score": 0.5,
      "forced_by_rule": false,
      "forced_by_semantic": false,
      "forced_by_functional": false,
      "hit": false
    },
    {
      "url": "https://arxiv.org/abs/2417.6355",
      "title": "Inference Latency Control: Method",
      "keyword_overlap_count": 0,
      "semantic_cosine": 0.47,
      "judge_score": 0.25,
      "forced_by_rule": false,
      "forced_by_semantic": false,
      "forced_by_functional": false,
      "hit": false
    },
    {
      "url": "https://arxiv.org/abs/2418.7728",
      "title": "Inference Latency Control: Analysis",
      "keyword_overlap_count": 0,
      "semantic_cosine": 0.41,
      "judge_score": 0.2,
      "forced_by_rule": false,
      "forced_by_semantic": false,
      "forced_by_functional": false,
      "hit": false
    },
    {
      "url": "https://arxiv.org/abs/2426.4982",
      "title": "Inference Latency Control: Survey",
      "keyword_overlap_count": 0,
      "semantic_cosine": 0.35,
      "judge_score": 0.15,
      "forced_by_rule": false,
      "forced_by_semantic": false,
      "forced_by_functional": false,
      "hit": false
    },
    {
      "url": "https://arxiv.org/abs/2427.6355",
      "title": "Inference Latency Control: Method",
      "keyword_overlap_count": 0,
      "semantic_cosine": 0.3,
      "judge_score": 0.15,
      "forced_by_rule": false,
      "forced_by_semantic": false,
      "forced_by_functional": false,
      "hit": false
    },
    {
      "url": "https://arxiv.org/abs/2428.7728",
      "title": "Inference Latency Control: Analysis",
      "keyword_overlap_count": 0,
      "semantic_cosine": 0.3,
      "judge_score": 0.15,
      "forced_by_rule": false,
      "forced_by_semantic": false,
      "forced_by_functional": false,
      "hit": false
    },
    {
      "url": "https://arxiv.org/abs/2429.9101",
      "title": "Tangential source-domain reference 3",
      "keyword_overlap_count": 0,
      "semantic_cosine": 0.3,
      "judge_score": 0.15,
      "forced_by_rule": false,
      "forced_by_semantic": false,
      "forced_by_functional": false,
      "hit": false
    }
  ],
  "total_hits": 1,
  "forced_by_rule_keyword_count": 0,
  "forced_by_semantic_count": 1,
  "forced_by_functional_count": 0,
  "additional_hits_from_semantic": 1,
  "additional_hits_from_functional": 0
}