{
  "atom_id": "ATOM_T009_S039_ANA_02",
  "atom_type": "ANALOGY",
  "paradigm_type": "analogy",
  "snippet_id": "S039",
  "transcript_id": "T009",
  "source_date": null,
  "target_date": null,
  "line_span": [
    520,
    533
  ],
  "verbatim_quote": "So, this is the big one this is the, the one I hear the most especially like candidates applying to a Asana they tell me, you know, I, I'd really like to work for, for a much smaller company, or start my own because. Then I have a much bigger slice of the pie, I'll have much more impact on how that company does and I'll have more equity.",
  "gloss": "[ANALOGY] So, this is the big one this is the, the one I hear the most especially like candidates applying to a Asana they tell me, you know, I, I'd really like to work for, for a much sm...",
  "extraction_pattern": "analogy_regex"
}