{
  "atom_id": "ATOM_T007_S002_ANA_02",
  "atom_type": "ANALOGY",
  "paradigm_type": "analogy",
  "snippet_id": "S002",
  "transcript_id": "T007",
  "source_date": null,
  "target_date": null,
  "line_span": [
    17,
    30
  ],
  "verbatim_quote": "C is like a very simple language just to give you a sense and. It would only require about 500 lines of C with no other dependencies to implement the the neural network architecture and that uses.",
  "gloss": "[ANALOGY] C is like a very simple language just to give you a sense and. It would only require about 500 lines of C with no other dependencies to implement the the neural network architec...",
  "extraction_pattern": "analogy_regex"
}